README.md
setup.py
pyzohodocs/__init__.py
pyzohodocs/conf.py
pyzohodocs/exceptions.py
pyzohodocs/pyzohodoc.py
pyzohodocs/zohoauth.py
pyzohodocs.egg-info/PKG-INFO
pyzohodocs.egg-info/SOURCES.txt
pyzohodocs.egg-info/dependency_links.txt
pyzohodocs.egg-info/not-zip-safe
pyzohodocs.egg-info/requires.txt
pyzohodocs.egg-info/top_level.txt