Metadata-Version: 2.1
Name: pyzohodocs
Version: 1.6
Summary: A Python Wrapper for the ZohoDocs API
Home-page: https://github.com/VarthanV/pyzohodocs
Author: Vishnu Varthan Rao
Author-email: vishnulatha006@gmail.com
License: MIT License
Keywords: zohodocs,zoho,docs,zohocrm,docx,xlxs
Platform: UNKNOWN
Classifier: Intended Audience :: Developers
Classifier: License :: OSI Approved :: MIT License
Classifier: Programming Language :: Python :: 3.3
Classifier: Operating System :: OS Independent
Classifier: Topic :: Software Development :: Libraries
Classifier: Topic :: Utilities
